Alexsecdemoraw.py
a-b/__init__.py
a-b/mymod2.py
a_b/__init__.py
a_b/unit.py
Alexsecdemo-5.2.9.dist-info/METADATA
Alexsecdemo-5.2.9.dist-info/WHEEL
Alexsecdemo-5.2.9.dist-info/top_level.txt
Alexsecdemo-5.2.9.dist-info/RECORD
