Metadata-Version: 2.1
Name: Alexsecdemo
Version: 5.2.9
Summary: A sample Python project, do not download it!
Author: Alex
Author-email: zhuzhuzhuzai@gmail.com
License: MIT
